zupa/__init__.py
zupa/__main__.py
zupa/system.py
zupa-0.0.2.dist-info/LICENSE
zupa-0.0.2.dist-info/WHEEL
zupa-0.0.2.dist-info/METADATA
zupa-0.0.2.dist-info/RECORD
